agentnexus/__init__.py
agentnexus/action_manager.py
agentnexus/base_types.py
agentnexus/event_dispatcher.py
agentnexus/llm_integration.py
agentnexus/manifest_generator.py
agentnexus/session_manager.py
agentnexus/ui_components.py
agentnexus/workflow_manager.py
agentnexus-0.0.1.dist-info/METADATA
agentnexus-0.0.1.dist-info/WHEEL
agentnexus-0.0.1.dist-info/top_level.txt
agentnexus-0.0.1.dist-info/RECORD
