Metadata-Version: 2.4
Name: agentnexus
Version: 0.0.1
Summary: Python Library for AI/LLM Agent Development with UI-Driven Workflows
Author: Muhammad Yossry
License: MIT
Project-URL: Homepage, https://github.com/MuhammadYossry/agentnexus
Project-URL: Documentation, https://muhammadyossry.github.io/agentnexus/
Project-URL: Bug Tracker, https://github.com/MuhammadYossry/agentnexus/issues
Project-URL: Changelog, https://github.com/MuhammadYossry/agentnexus/blob/main/CHANGELOG.md
Keywords: ai,llm,agents,langchain,openai,genai,artificial-intelligence,machine-learning,nlp,fastapi,ui-components,workflow,ai-agents,generative-ai,large-language-models
Classifier: Development Status :: 3 - Alpha
Classifier: Intended Audience :: Developers
Classifier: Intended Audience :: Science/Research
Classifier: License :: OSI Approved :: MIT License
Classifier: Programming Language :: Python :: 3.12
Classifier: Programming Language :: Python :: 3.13
Classifier: Topic :: Scientific/Engineering :: Artificial Intelligence
Classifier: Topic :: Software Development :: Libraries :: Application Frameworks
Classifier: Topic :: Software Development :: User Interfaces
Classifier: Framework :: FastAPI
Requires-Python: <4.0,>=3.12
Requires-Dist: fastapi>=0.115.6
Requires-Dist: pydantic>=2.10.3
Requires-Dist: uvicorn>=0.32.1
Requires-Dist: loguru>=0.7.3
Requires-Dist: jinja2>=3.1.5
Requires-Dist: redis>=5.2.1
Requires-Dist: pydantic-settings>=2.7.1
Requires-Dist: openai>=1.59.3
